seJsonDB/__about__.py
seJsonDB/__init__.py
seJsonDB/db.py
seJsonDB/db_types.py
seJsonDB/errors.py
sejsondb-2025.1.0rc2.dist-info/LICENSE
sejsondb-2025.1.0rc2.dist-info/METADATA
sejsondb-2025.1.0rc2.dist-info/WHEEL
sejsondb-2025.1.0rc2.dist-info/top_level.txt
sejsondb-2025.1.0rc2.dist-info/RECORD
