Metadata-Version: 2.1
Name: sejsondb
Version: 2025.1.0rc2
Summary: A Simple , Lightweight , Efficient JSON based database for Python. 
Author-email: Cybernetic Innovations <github@cyberneticinnovations.com>
Classifier: License :: OSI Approved :: MIT License
Requires-Python: >=3.10
License-File: LICENSE
Requires-Dist: ujson==5.10.0
